azure_recommendations_13/__init__.py
azure_recommendations_13/recommendation/__init__.py
azure_recommendations_13/recommendation/advisor_recommendations.py
azure_recommendations_13/recommendation/network_recommendations.py
azure_recommendations_13/recommendation/utils.py
azure_recommendations_13/recommendation/vm_recommendations.py
azure_recommendations_13-0.2.1.dist-info/LICENCE
azure_recommendations_13-0.2.1.dist-info/METADATA
azure_recommendations_13-0.2.1.dist-info/WHEEL
azure_recommendations_13-0.2.1.dist-info/top_level.txt
azure_recommendations_13-0.2.1.dist-info/RECORD
